esenin/__init__.py
esenin-python/__init__.py
esenin_python/__init__.py
esenin-0.1.0.dist-info/LICENSE
esenin-0.1.0.dist-info/METADATA
esenin-0.1.0.dist-info/WHEEL
esenin-0.1.0.dist-info/top_level.txt
esenin-0.1.0.dist-info/RECORD
