Metadata-Version: 2.1
Name: esenin
Version: 0.1.0
Summary: Python wrapper for esenin.
Home-page: https://github.com/esenin-org/esenin-python
Author: vovapolu
Author-email: vovapolu@gmail.com
License: UNKNOWN
Platform: UNKNOWN
Classifier: Programming Language :: Python :: 3
Classifier: License :: OSI Approved :: GNU Lesser General Public License v3 or later (LGPLv3+)
Classifier: Operating System :: OS Independent
